concurrency/__init__.py
concurrency/messages.py
concurrency/processes.py
concurrency/threads.py
concurrency-0.1.0.dist-info/METADATA
concurrency-0.1.0.dist-info/RECORD
concurrency-0.1.0.dist-info/WHEEL
concurrency-0.1.0.dist-info/top_level.txt
