Metadata-Version: 2.1
Name: concurrency
Version: 0.1.0
Summary: Assortment of concurrency related python tools
Home-page: https://github.com/dnut/concurrency
Author: Drew Nutter
Author-email: drew@drewnutter.com
License: GPLv3
Platform: UNKNOWN
